invenio_workflows_tugraz/__init__.py
invenio_workflows_tugraz/cli.py
invenio_workflows_tugraz/config.py
invenio_workflows_tugraz/ext.py
invenio_workflows_tugraz/proxies.py
invenio_workflows_tugraz/types.py
invenio_workflows_tugraz/workflows.py
invenio_workflows_tugraz/data/iso6393.json
invenio_workflows_tugraz/imoox/__init__.py
invenio_workflows_tugraz/imoox/visitor.py
invenio_workflows_tugraz/imoox/workflows.py
invenio_workflows_tugraz/oer/__init__.py
invenio_workflows_tugraz/oer/convert.py
invenio_workflows_tugraz/oer/workflow.py
invenio_workflows_tugraz/openaccess/__init__.py
invenio_workflows_tugraz/openaccess/api.py
invenio_workflows_tugraz/openaccess/config.py
invenio_workflows_tugraz/openaccess/convert.py
invenio_workflows_tugraz/openaccess/models.py
invenio_workflows_tugraz/openaccess/service.py
invenio_workflows_tugraz/openaccess/types.py
invenio_workflows_tugraz/openaccess/utils.py
invenio_workflows_tugraz/openaccess/workflow.py
invenio_workflows_tugraz/openaccess/alembic/74b15cacffbc_create_openaccess_branch.py
invenio_workflows_tugraz/openaccess/alembic/bf15edb5b389_create_openaccess_tables.py
invenio_workflows_tugraz/teachcenter/__init__.py
invenio_workflows_tugraz/teachcenter/config.py
invenio_workflows_tugraz/teachcenter/types.py
invenio_workflows_tugraz/teachcenter/visitor.py
invenio_workflows_tugraz/teachcenter/workflows.py
invenio_workflows_tugraz/theses/__init__.py
invenio_workflows_tugraz/theses/api.py
invenio_workflows_tugraz/theses/cli.py
invenio_workflows_tugraz/theses/config.py
invenio_workflows_tugraz/theses/convert.py
invenio_workflows_tugraz/theses/decorators.py
invenio_workflows_tugraz/theses/jobs.py
invenio_workflows_tugraz/theses/models.py
invenio_workflows_tugraz/theses/service.py
invenio_workflows_tugraz/theses/tasks.py
invenio_workflows_tugraz/theses/theses.py
invenio_workflows_tugraz/theses/types.py
invenio_workflows_tugraz/theses/views.py
invenio_workflows_tugraz/theses/alembic/02845ec6893c_update_theses_tables.py
invenio_workflows_tugraz-0.11.0.dist-info/licenses/AUTHORS.rst
invenio_workflows_tugraz-0.11.0.dist-info/licenses/LICENSE
invenio_workflows_tugraz-0.11.0.dist-info/METADATA
invenio_workflows_tugraz-0.11.0.dist-info/WHEEL
invenio_workflows_tugraz-0.11.0.dist-info/entry_points.txt
invenio_workflows_tugraz-0.11.0.dist-info/top_level.txt
invenio_workflows_tugraz-0.11.0.dist-info/RECORD
