Metadata-Version: 2.4
Name: invenio-workflows-tugraz
Version: 0.11.0
Summary: "Package serves as a place for the workflows of the repository of the TU Graz."
Home-page: https://github.com/tu-graz-library/invenio-workflows-tugraz
Author: Graz University of Technology
Author-email: info@tugraz.at
License: MIT
Keywords: invenio workflows TUGraz
Platform: any
Classifier: Programming Language :: Python :: 3.12
Classifier: Programming Language :: Python :: 3.13
Classifier: Development Status :: 5 - Production/Stable
Requires-Python: >=3.12
License-File: LICENSE
License-File: AUTHORS.rst
Requires-Dist: invenio-alma>=0.7.1
Requires-Dist: invenio-campusonline>=0.1.1
Requires-Dist: invenio-jobs>=3.0.0
Requires-Dist: invenio-moodle>=1.0.0
Requires-Dist: invenio-pure>=0.1.1
Requires-Dist: invenio-records-lom>=0.18.0
Requires-Dist: invenio-records-marc21>=0.13.0
Provides-Extra: tests
Requires-Dist: invenio-app>=2.0.0; extra == "tests"
Requires-Dist: invenio-search[opensearch2]>=2.1.0; extra == "tests"
Requires-Dist: invenio-rdm-records>=19.0.0; extra == "tests"
Requires-Dist: pytest-black-ng>=0.4.0; extra == "tests"
Requires-Dist: pytest-invenio>=1.4.0; extra == "tests"
Requires-Dist: ruff>=0.4.10; extra == "tests"
Requires-Dist: sphinx>=4.5; extra == "tests"
Dynamic: license-file
